django_theme_css_loader/__init__.py
django_theme_css_loader/apps.py
django_theme_css_loader/static/django_theme_css_loader/loader.js
django_theme_css_loader/static/django_theme_css_loader/loader.min.js
django_theme_css_loader/widgets.py
django_theme_css_loader-1.0.1.dist-info/LICENSE
django_theme_css_loader-1.0.1.dist-info/METADATA
django_theme_css_loader-1.0.1.dist-info/WHEEL
django_theme_css_loader-1.0.1.dist-info/RECORD
