Metadata-Version: 2.1
Name: django-theme-css-loader
Version: 1.0.1
Summary: Load different CSS in Django admin site when switching between dark/light mode
License: MIT
Author: rabbit-aaron
Author-email: rabbit.aaron@gmail.com
Requires-Python: >=3.8
Classifier: License :: OSI Approved :: MIT License
Classifier: Programming Language :: Python :: 3
Classifier: Programming Language :: Python :: 3.8
Classifier: Programming Language :: Python :: 3.9
Classifier: Programming Language :: Python :: 3.10
Classifier: Programming Language :: Python :: 3.11
Classifier: Programming Language :: Python :: 3.12
Requires-Dist: django (>=3.2)
